semanticmatcher/__init__.py
semanticmatcher/join.py
semanticmatcher/search.py
semanticmatcher/tables.py
semanticmatcher-0.0.2.dist-info/METADATA
semanticmatcher-0.0.2.dist-info/WHEEL
semanticmatcher-0.0.2.dist-info/top_level.txt
semanticmatcher-0.0.2.dist-info/RECORD
