Metadata-Version: 2.1
Name: semanticmatcher
Version: 0.0.2
Summary: Semantic search of text and semanic matching of tables using FAISS
Author: Aayush Choudhury
Author-email: Aayush Choudhury <aayush.choudhury@kpmg.co.uk>
Project-URL: Homepage, https://github.com/Aayushchou/semantic-matcher
Project-URL: Bug Tracker, https://github.com/Aayushchou/semantic-matcher/issues
Platform: unix
Platform: linux
Platform: osx
Platform: cygwin
Platform: win32
Classifier: Programming Language :: Python :: 3
Classifier: License :: OSI Approved :: MIT License
Classifier: Operating System :: OS Independent
Requires-Python: >=3.8
Requires-Dist: pandas
Requires-Dist: faiss-cpu
Requires-Dist: sentence-transformers
Provides-Extra: dev
Requires-Dist: black ; extra == 'dev'
Requires-Dist: pylint ; extra == 'dev'
Provides-Extra: gpu
Requires-Dist: faiss-gpu ; extra == 'gpu'
Provides-Extra: test
Requires-Dist: faker ; extra == 'test'
Requires-Dist: pytest ; extra == 'test'
